MANIFEST.in
setup.py
ltmo/__init__.py
ltmo/feeds.py
ltmo/forms.py
ltmo/manage.py
ltmo/models.py
ltmo/settings.py
ltmo/urls.py
ltmo/views.py
ltmo.egg-info/PKG-INFO
ltmo.egg-info/SOURCES.txt
ltmo.egg-info/dependency_links.txt
ltmo.egg-info/entry_points.txt
ltmo.egg-info/requires.txt
ltmo.egg-info/top_level.txt
ltmo/media/style.css
ltmo/templates/404.html
ltmo/templates/500.html
ltmo/templates/banners.html
ltmo/templates/detail.html
ltmo/templates/index.html
ltmo/templates/success.json
ltmo/templates/feeds/description.html
ltmo/templates/pagination/pagination.html
ltmo/templatetags/__init__.py
ltmo/templatetags/gravatar.py
ltmo/templatetags/macros.py