Metadata-Version: 1.0
Name: ltmo
Version: 0.12
Summary: Un sitio para los amigos
Home-page: http://ltmo.com.ar
Author: Matías Iturburu, Francisco Herrero
Author-email: maturburu@gmail.com, francisco.herrero@gmail.com
License: UNKNOWN
Platform: UNKNOWN
